{
  "repositories": [
    {
      "name": "Unfoundry",
      "folder": "A_Unfoundry",
      "url": "https://github.com/erkle64/Unfoundry/releases/download/v0.2.2/Unfoundry.mod",
      "home": "https://github.com/erkle64/Unfoundry/",
      "requirements": [
      ]
    },
    {
      "name": "BulkDemolishTerrain",
      "folder": "BulkDemolishTerrain",
      "url": "https://github.com/erkle64/BulkDemolishTerrain/releases/download/v1.2.0/BulkDemolishTerrain.mod",
      "home": "https://github.com/erkle64/BulkDemolishTerrain/",
      "requirements": [
        "Unfoundry"
      ]
    },
    {
      "name": "Duplicationer",
      "folder": "Duplicationer",
      "url": "https://github.com/erkle64/Duplicationer/releases/download/v0.3.5/Duplicationer.mod",
      "home": "https://github.com/erkle64/Duplicationer/",
      "requirements": [
        "Unfoundry"
      ]
    },
    {
      "name": "Embiggenator",
      "folder": "Embiggenator",
      "url": "https://github.com/erkle64/Embiggenator/releases/download/v1.1.0/Embiggenator.mod",
      "home": "https://github.com/erkle64/Embiggenator/",
      "requirements": [
        "Unfoundry"
      ]
    },
    {
      "name": "FoundryCommands",
      "folder": "FoundryCommands",
      "url": "https://github.com/erkle64/FoundryCommands/releases/download/v1.5.2/FoundryCommands.mod",
      "home": "https://github.com/erkle64/FoundryCommands/",
      "requirements": [
        "Unfoundry"
      ]
    },
    {
      "name": "OreMultiplier",
      "folder": "OreMultiplier",
      "url": "https://github.com/erkle64/OreMultiplier/releases/download/v0.1.0/OreMultiplier.mod",
      "home": "https://github.com/erkle64/OreMultiplier/",
      "requirements": [
        "Unfoundry"
      ]
    },
    {
      "name": "StepUp2TheBlocks",
      "folder": "StepUp2TheBlocks",
      "url": "https://github.com/erkle64/StepUp2TheBlocks/releases/download/v0.1.0/StepUp2TheBlocks.mod",
      "home": "https://github.com/erkle64/StepUp2TheBlocks/",
      "requirements": [
        "Unfoundry"
      ]
    }
  ]
}
